finditcli/cli.py
finditcli/constants.py
finditcli/exceptions.py
finditcli/finder.py
finditcli/utils.py
finditcli-0.1.2.dist-info/METADATA
finditcli-0.1.2.dist-info/WHEEL
finditcli-0.1.2.dist-info/entry_points.txt
finditcli-0.1.2.dist-info/RECORD
