Metadata-Version: 2.1
Name: finditcli
Version: 0.1.2
Summary: 
Author: dgeison
Author-email: dgeison.peixoto@gmail.com
Requires-Python: >=3.10,<4.0
Classifier: Programming Language :: Python :: 3
Classifier: Programming Language :: Python :: 3.10
Classifier: Programming Language :: Python :: 3.11
Requires-Dist: black (>=23.3.0,<24.0.0)
Requires-Dist: click (>=8.1.3,<9.0.0)
Requires-Dist: datetime (>=5.1,<6.0)
Requires-Dist: isort (>=5.12.0,<6.0.0)
Requires-Dist: tabulate (>=0.9.0,<0.10.0)
